docker_ready_cli/__init__.py
docker_ready_cli/commands/__init__.py
docker_ready_cli/commands/ps.py
docker_ready_cli/commands/run.py
docker_ready_cli/commands/show.py
docker_ready_cli/main.py
docker_ready_cli/utils/__init__.py
docker_ready_cli/utils/tools.py
docker_ready_cli-0.2.0.dist-info/METADATA
docker_ready_cli-0.2.0.dist-info/WHEEL
docker_ready_cli-0.2.0.dist-info/entry_points.txt
docker_ready_cli-0.2.0.dist-info/RECORD
